rangerjson/__init__.py
rangerjson/ranger.py
rangerjson-0.1.6.dist-info/WHEEL
rangerjson-0.1.6.dist-info/METADATA
rangerjson-0.1.6.dist-info/RECORD
